spidar/__init__.py
spidar/css.py
spidar/dammit.py
spidar/diagnose.py
spidar/element.py
spidar/formatter.py
spidar/builder/__init__.py
spidar/builder/_html5lib.py
spidar/builder/_htmlparser.py
spidar/builder/_lxml.py
spidar/tests/__init__.py
spidar/tests/test_builder.py
spidar/tests/test_builder_registry.py
spidar/tests/test_css.py
spidar/tests/test_dammit.py
spidar/tests/test_docs.py
spidar/tests/test_element.py
spidar/tests/test_formatter.py
spidar/tests/test_fuzz.py
spidar/tests/test_html5lib.py
spidar/tests/test_htmlparser.py
spidar/tests/test_lxml.py
spidar/tests/test_navigablestring.py
spidar/tests/test_pageelement.py
spidar/tests/test_soup.py
spidar/tests/test_tag.py
spidar/tests/test_tree.py
spidar/tests/fuzz/clusterfuzz-testcase-minimized-bs4_fuzzer-4670634698080256.testcase
spidar/tests/fuzz/clusterfuzz-testcase-minimized-bs4_fuzzer-4818336571064320.testcase
spidar/tests/fuzz/clusterfuzz-testcase-minimized-bs4_fuzzer-4999465949331456.testcase
spidar/tests/fuzz/clusterfuzz-testcase-minimized-bs4_fuzzer-5000587759190016.testcase
spidar/tests/fuzz/clusterfuzz-testcase-minimized-bs4_fuzzer-5167584867909632.testcase
spidar/tests/fuzz/clusterfuzz-testcase-minimized-bs4_fuzzer-5270998950477824.testcase
spidar/tests/fuzz/clusterfuzz-testcase-minimized-bs4_fuzzer-5375146639360000.testcase
spidar/tests/fuzz/clusterfuzz-testcase-minimized-bs4_fuzzer-5492400320282624.testcase
spidar/tests/fuzz/clusterfuzz-testcase-minimized-bs4_fuzzer-5703933063462912.testcase
spidar/tests/fuzz/clusterfuzz-testcase-minimized-bs4_fuzzer-5843991618256896.testcase
spidar/tests/fuzz/clusterfuzz-testcase-minimized-bs4_fuzzer-5984173902397440.testcase
spidar/tests/fuzz/clusterfuzz-testcase-minimized-bs4_fuzzer-6124268085182464.testcase
spidar/tests/fuzz/clusterfuzz-testcase-minimized-bs4_fuzzer-6241471367348224.testcase
spidar/tests/fuzz/clusterfuzz-testcase-minimized-bs4_fuzzer-6306874195312640.testcase
spidar/tests/fuzz/clusterfuzz-testcase-minimized-bs4_fuzzer-6450958476902400.testcase
spidar-0.0.1.dist-info/METADATA
spidar-0.0.1.dist-info/WHEEL
spidar-0.0.1.dist-info/licenses/LICENSE
spidar-0.0.1.dist-info/RECORD
